src/attendance_manager.py
src/browser.py
src/dakoker.py
src/stamp_manager.py
src/user_info_manager.py
src/utils/calc.py
src/utils/color.py
dakoker-0.1.31.dist-info/entry_points.txt
dakoker-0.1.31.dist-info/LICENSE
dakoker-0.1.31.dist-info/WHEEL
dakoker-0.1.31.dist-info/METADATA
dakoker-0.1.31.dist-info/RECORD
