Metadata-Version: 2.1
Name: dakoker
Version: 0.1.31
Summary: 
License: MIT
Author: nixiesquid
Author-email: audu817@gmail.com
Requires-Python: >=3.9,<4.0
Classifier: License :: OSI Approved :: MIT License
Classifier: Programming Language :: Python :: 3
Classifier: Programming Language :: Python :: 3.9
Requires-Dist: bs4 (>=0.0.1,<0.0.2)
Requires-Dist: fire (>=0.3.1,<0.4.0)
Requires-Dist: halo (>=0.0.29,<0.0.30)
Requires-Dist: keyring (>=21.2.1,<22.0.0)
Requires-Dist: pick (>=0.6.7,<0.7.0)
Requires-Dist: requests (>=2.24.0,<3.0.0)
Requires-Dist: selenium (>=3.141.0,<4.0.0)
